qadence2/__init__.py
qadence2/compiler.py
qadence2/utils.py
qadence2/extensions/__init__.py
qadence2/extensions/legacy/__init__.py
qadence2/extensions/legacy/model.py
qadence2/extensions/legacy/operators.py
qadence2/extensions/legacy/utils.py
qadence2-0.2.0.dist-info/METADATA
qadence2-0.2.0.dist-info/WHEEL
qadence2-0.2.0.dist-info/RECORD
