Metadata-Version: 2.4
Name: qadence2
Version: 0.2.0
Summary: Qadence 2
Project-URL: Issues, https://github.com/pasqal-io/qadence2-core/issues
Project-URL: Source, https://github.com/pasqal-io/qadence2-core
Author-email: Eduardo Maschio <eduardo.maschio@pasqal.com>, Kaonan Micadei <kaonan.micadei@pasqal.com>, Dominik Seitz <dominik.seitz@pasqal.com>, Roland Guichard <roland.guichard@pasqal.com>, João Moutinho <joao.moutinho@pasqal.com>, Pim Venderbosch <pim.venderbosch@pasqal.com>
License: Apache 2.0
Keywords: quantum
Classifier: Development Status :: 4 - Beta
Classifier: Programming Language :: Python
Classifier: Programming Language :: Python :: 3.10
Classifier: Programming Language :: Python :: 3.11
Classifier: Programming Language :: Python :: 3.12
Classifier: Programming Language :: Python :: Implementation :: CPython
Classifier: Programming Language :: Python :: Implementation :: PyPy
Requires-Python: <3.13,>=3.10
Requires-Dist: pyqtorch
Requires-Dist: qadence2-expressions
Requires-Dist: qadence2-ir
Requires-Dist: qadence2-platforms
Provides-Extra: extras
